ipyd3/__init__.py
ipyd3/_version.py
ipyd3/graph.py
ipyd3/hierarchical.py
ipyd3/network_traitlet.py
ipyd3/labextension/package.json
ipyd3/labextension/static/121.a11ef198235712d5c60b.js
ipyd3/labextension/static/154.51690fae5276f4a7acd5.js
ipyd3/labextension/static/261.af32828bf4be63d12e26.js
ipyd3/labextension/static/373c04fd2418f5c77eea49d514731058f1907a94ff3b4e5d7c3e5767e8b53d8b.eot
ipyd3/labextension/static/3f6d3488cf65374f6f676c315340b0ac2be832bd55240c809448e36ef9b96326.woff
ipyd3/labextension/static/486.029244b9e89b21b7e6fa.js
ipyd3/labextension/static/486.029244b9e89b21b7e6fa.js.LICENSE.txt
ipyd3/labextension/static/550.8fe2b06ebee6b0f9d2aa.js
ipyd3/labextension/static/568.3510f62eff371d73999a.js
ipyd3/labextension/static/68.2cc696d3530936662ac6.js
ipyd3/labextension/static/716.d564332eee5e3a3551b4.js
ipyd3/labextension/static/79d088064beb3826054fb88165416235897a856ca952fca1498b1c59b16aaa48.eot
ipyd3/labextension/static/8ea8791754915a898a3100e63e32978a6d1763be6df8e73a39d3a90d691cdeef.woff2
ipyd3/labextension/static/909.eada4d6d33c969477747.js
ipyd3/labextension/static/909.eada4d6d33c969477747.js.LICENSE.txt
ipyd3/labextension/static/9674eb1bd5504717903837093a67668ea88f2ed006d91367d0d4b7aa1f9211fc.svg
ipyd3/labextension/static/9834b82ad26e2a37583d22676a12dd2eb0fe7c80356a2114d0db1aa8b3899537.woff2
ipyd3/labextension/static/a3b9817780214caf01e8aec20bcdc2305a1ff34a15fae81ecd0923df9cd5cd0a.svg
ipyd3/labextension/static/af6397503fcefbd613976c21ad5c1e37298c18bbe07d096db03ccd3af6e05ba8.ttf
ipyd3/labextension/static/be0a084962d8066884f7fe9bd27ec16e51f5a93b72a502c92c5a24dc87eb2ebc.svg
ipyd3/labextension/static/cb9e9e693192413cde2b1f21c1dc1d44b6fe7b27cc2b458e8b359d18f9ff8f4e.woff
ipyd3/labextension/static/cda59d6efffa685830fd95b55f64ae9cb51279cd34b2410b69f84c7ec30157d9.ttf
ipyd3/labextension/static/e4299464e7b012968eed63ac2db1c9509f56bca409ef9f71f2926a8c3c80b2a9.eot
ipyd3/labextension/static/e42a88444448ac3d60549cc7c1ff2c8a9cac721034c073d80a14a44e79730cca.woff2
ipyd3-3.0.1.dist-info/METADATA
ipyd3-3.0.1.dist-info/WHEEL
ipyd3-3.0.1.dist-info/top_level.txt
ipyd3-3.0.1.dist-info/RECORD
