Metadata-Version: 2.1
Name: ipyd3
Version: 3.0.1
Summary: Library for visualizing D3.js inside Jupyter.
Home-page: https://github.com//ipyd3
Author: David Fernandez
Author-email: teia.eng.14@gmail.com
License: BSD 3-Clause License
Keywords: ipython,widgets,Jupyter,JupyterLab,JupyterLab3
Classifier: License :: OSI Approved :: BSD License
Classifier: Development Status :: 4 - Beta
Classifier: Framework :: IPython
Classifier: Intended Audience :: Developers
Classifier: Intended Audience :: Science/Research
Classifier: Programming Language :: Python
Classifier: Programming Language :: Python :: 3.7
Classifier: Programming Language :: Python :: 3.8
Classifier: Programming Language :: Python :: 3.9
Classifier: Programming Language :: Python :: 3.10
Classifier: Framework :: Jupyter
Classifier: Framework :: Jupyter :: JupyterLab
Classifier: Framework :: Jupyter :: JupyterLab :: 3
Classifier: Framework :: Jupyter :: JupyterLab :: Extensions
Classifier: Framework :: Jupyter :: JupyterLab :: Extensions :: Prebuilt
Requires-Python: >=3.7
Requires-Dist: ipywidgets (<9,>=7.6.0)
